INSTALL.rst
LICENSE
MANIFEST.in
README.rst
VERSION
requirements.txt
setup.py
src/colortools/__init__.py
src/colortools/__meta__.py
src/colortools/base.py
src/colortools.egg-info/PKG-INFO
src/colortools.egg-info/SOURCES.txt
src/colortools.egg-info/dependency_links.txt
src/colortools.egg-info/not-zip-safe
src/colortools.egg-info/requires.txt
src/colortools.egg-info/top_level.txt