Metadata-Version: 1.1
Name: colortools
Version: 0.1.2
Summary: A short description for your project.
Home-page: UNKNOWN
Author: Fábio Macêdo Mendes
Author-email: fabiomacedomendes@gmail.com
License: UNKNOWN
Platform: any
Classifier: Development Status :: 3 - Alpha
Classifier: Intended Audience :: Developers
Classifier: License :: OSI Approved :: GNU General Public License (GPL)
Classifier: Operating System :: POSIX
Classifier: Programming Language :: Python
Classifier: Topic :: Software Development :: Libraries
